orchestr8/__init__.py
orchestr8/_paths.py
orchestr8/directory_tracker.py
orchestr8/logger.py
orchestr8/sandbox_client.py
orchestr8/shell.py
orchestr8/adapter/__init__.py
orchestr8/adapter/base.py
orchestr8/adapter/function.py
orchestr8/adapter/struct.py
orchestr8/adapter/utils.py
orchestr8/execution_runtime/__init__.py
orchestr8/execution_runtime/package_utils.py
orchestr8/execution_runtime/stdlib.txt
orchestr8/oauth_flow/__init__.py
orchestr8/oauth_flow/redirect_server.py
orchestr8-0.0.3.dist-info/LICENSE
orchestr8-0.0.3.dist-info/METADATA
orchestr8-0.0.3.dist-info/WHEEL
orchestr8-0.0.3.dist-info/top_level.txt
orchestr8-0.0.3.dist-info/RECORD
