Metadata-Version: 2.1
Name: orchestr8
Version: 0.0.3
Summary: A versatile collection of independent components crafted to simplify task automation, particularly for AI workflows.
Author-email: Harsh Verma <synacktra.work@gmail.com>
Project-URL: Documentation, https://synacktraa.github.io/orchestr8/
Project-URL: Homepage, https://synacktraa.github.io/orchestr8/
Project-URL: Repository, https://github.com/synacktraa/orchestr8
Keywords: python
Classifier: Intended Audience :: Developers
Classifier: Programming Language :: Python
Classifier: Programming Language :: Python :: 3
Classifier: Programming Language :: Python :: 3.9
Classifier: Programming Language :: Python :: 3.10
Classifier: Programming Language :: Python :: 3.11
Classifier: Programming Language :: Python :: 3.12
Classifier: Programming Language :: Python :: 3.13
Classifier: Topic :: Software Development :: Libraries :: Python Modules
Requires-Python: <4.0,>=3.9
License-File: LICENSE
Requires-Dist: loguru>=0.7.0
Provides-Extra: adapter
Requires-Dist: docstring-parser>=0.15; extra == "adapter"
Requires-Dist: jsonref>=1.1.0; extra == "adapter"
Requires-Dist: pydantic<=2.9.0,>=2.0.0; extra == "adapter"
Provides-Extra: execution-runtime
Requires-Dist: docker>=7.1.0; extra == "execution-runtime"
Requires-Dist: packaging>=24.1; extra == "execution-runtime"
Requires-Dist: uv>=0.5.0; extra == "execution-runtime"
Provides-Extra: sandbox-client
Requires-Dist: docker>=7.1.0; extra == "sandbox-client"
Provides-Extra: shell
Requires-Dist: docker>=7.1.0; extra == "shell"
Provides-Extra: all
Requires-Dist: docker>=7.1.0; extra == "all"
Requires-Dist: docstring-parser>=0.15; extra == "all"
Requires-Dist: jsonref>=1.1.0; extra == "all"
Requires-Dist: packaging>=24.1; extra == "all"
Requires-Dist: pydantic<=2.9.0,>=2.0.0; extra == "all"
Requires-Dist: uv>=0.5.0; extra == "all"
